LICENSE
MANIFEST.in
bootstrap.py
buildout.cfg
setup.cfg
setup.py
examples/group.diag
examples/multibyte.diag
examples/numbered.diag
examples/screen.diag
examples/simple.diag
src/README.txt
src/TODO.txt
src/ikazuchi/__init__.py
src/ikazuchi.plugins.blockdiag.egg-info/PKG-INFO
src/ikazuchi.plugins.blockdiag.egg-info/SOURCES.txt
src/ikazuchi.plugins.blockdiag.egg-info/dependency_links.txt
src/ikazuchi.plugins.blockdiag.egg-info/entry_points.txt
src/ikazuchi.plugins.blockdiag.egg-info/namespace_packages.txt
src/ikazuchi.plugins.blockdiag.egg-info/requires.txt
src/ikazuchi.plugins.blockdiag.egg-info/top_level.txt
src/ikazuchi/plugins/__init__.py
src/ikazuchi/plugins/_blockdiag.py
src/ikazuchi/tests/test_pep8.py